{
    "builders": [
        {
            "name": "ami",
            "type": "amazon-ebs",
            "profile": "default",
            "region": "us-east-2",
            "instance_type": "t2.micro",
            "source_ami_filter": {
                "filters": { "name": "Windows_Server-2019-English-Full-Base-*" },
                "owners": ["amazon"],
                "most_recent": true
            },
            "ami_name": "packer-ws2019gui-{{isotime | clean_resource_name}}",
            "user_data_file": "scripts/user_data.ps1",
            "communicator": "winrm",
            "winrm_username": "Administrator",
            "winrm_timeout": "10m",
            "winrm_use_ssl": true,
            "winrm_insecure": true,
            "winrm_use_ntlm": true,
            "tags": {
                "project": "packer",
                "platform": "windows_server",
                "version": "2019gui",
                "created": "{{isotime | clean_resource_name}}"
            },
            "snapshot_tags": {
                "project": "packer",
                "platform": "windows_server",
                "version": "2019gui",
                "created": "{{isotime | clean_resource_name}}"
            }
        }
    ],

    "provisioners": [
        {
            "type": "powershell",
            "script": "scripts/config_firewall.ps1"
        },
        {
            "type": "powershell",
            "inline": [
                "C:\\ProgramData\\Amazon\\EC2-Windows\\Launch\\Scripts\\InitializeInstance.ps1 -Schedule",
                "C:\\ProgramData\\Amazon\\EC2-Windows\\Launch\\Scripts\\SysprepInstance.ps1 -NoShutdown"
            ]
        }
    ]

}
